microsoftdesigner/__init__.py
microsoftdesigner/__main__.py
microsoftdesigner/constants.py
microsoftdesigner/gen_images.py
microsoftdesigner/logger.py
microsoftdesigner/utils.py
microsoftdesigner-0.0.13.dist-info/LICENSE
microsoftdesigner-0.0.13.dist-info/METADATA
microsoftdesigner-0.0.13.dist-info/WHEEL
microsoftdesigner-0.0.13.dist-info/RECORD
