Metadata-Version: 2.3
Name: microsoftdesigner
Version: 0.0.13
Summary: High quality image generation by Microsoft Designer. Reverse engineered API.
License: GNU General Public License v3.0
Keywords: msdesigner,microsoft,designer,api
Author: imnotdev25
Author-email: 85677268+imnotdev25@users.noreply.github.com
Requires-Python: >=3.8
Classifier: License :: Other/Proprietary License
Classifier: Programming Language :: Python :: 3
Classifier: Programming Language :: Python :: 3.8
Classifier: Programming Language :: Python :: 3.9
Classifier: Programming Language :: Python :: 3.10
Classifier: Programming Language :: Python :: 3.11
Classifier: Programming Language :: Python :: 3.12
Classifier: Programming Language :: Python :: 3.13
Requires-Dist: beautifulsoup4 (>=4.12.3)
Requires-Dist: httpx (>=0.28.1)
Requires-Dist: lxml (>=5.3)
Requires-Dist: python-dotenv (>=0.21.1)
Project-URL: Homepage, https://github.com/imnotdev25/Msdesigner-api
Project-URL: Issues, https://github.com/imnotdev25/Msdesigner-api/issues
